{"edge_count":225,"graph":{"edges":[{"is_cross_platform":false,"source":"Alameda Research","target":"SBF","type":"DISLIKE_COMMENT, LIKE_POST","weight":6},{"is_cross_platform":false,"source":"Binance","target":"SBF","type":"DISLIKE_COMMENT, LIKE_POST","weight":5},{"is_cross_platform":false,"source":"FTX","target":"BTC","type":"LIKE_COMMENT","weight":5},{"is_cross_platform":false,"source":"Voyager","target":"Alameda Research","type":"LIKE_COMMENT, LIKE_POST","weight":5},{"is_cross_platform":false,"source":"FTX","target":"SBF","type":"DISLIKE_COMMENT, LIKE_POST","weight":4},{"is_cross_platform":false,"source":"SBF","target":"FTX","type":"DISLIKE_COMMENT, DISLIKE_POST, LIKE_POST","weight":4},{"is_cross_platform":false,"source":"Aave","target":"SBF","type":"DISLIKE_COMMENT","weight":4},{"is_cross_platform":false,"source":"FTT","target":"Caroline Ellison","type":"DISLIKE_POST, LIKE_COMMENT, LIKE_POST","weight":4},{"is_cross_platform":false,"source":"Voyager","target":"FTX","type":"LIKE_COMMENT, LIKE_POST","weight":4},{"is_cross_platform":false,"source":"Luna","target":"Alameda Research","type":"LIKE_COMMENT","weight":4},{"is_cross_platform":false,"source":"Luna","target":"FTX","type":"LIKE_COMMENT, LIKE_POST","weight":3},{"is_cross_platform":false,"source":"MakerDAO","target":"Caroline Ellison","type":"DISLIKE_POST, LIKE_POST","weight":3},{"is_cross_platform":false,"source":"Alameda Research","target":"Caroline Ellison","type":"DISLIKE_POST, LIKE_COMMENT, LIKE_POST","weight":3},{"is_cross_platform":false,"source":"Three Arrows Capital","target":"FTX","type":"LIKE_COMMENT, LIKE_POST","weight":3},{"is_cross_platform":false,"source":"MakerDAO","target":"FTX","type":"LIKE_COMMENT, LIKE_POST","weight":3},{"is_cross_platform":false,"source":"BTC","target":"Caroline Ellison","type":"DISLIKE_POST, LIKE_POST","weight":3},{"is_cross_platform":false,"source":"FTT","target":"FTX","type":"DISLIKE_POST, LIKE_COMMENT, LIKE_POST","weight":3},{"is_cross_platform":false,"source":"Caroline Ellison","target":"BTC","type":"LIKE_COMMENT","weight":3},{"is_cross_platform":false,"source":"Three Arrows Capital","target":"Curve","type":"LIKE_COMMENT, LIKE_POST","weight":3},{"is_cross_platform":false,"source":"Three Arrows Capital","target":"BTC","type":"LIKE_COMMENT","weight":3},{"is_cross_platform":false,"source":"Aave","target":"Alameda Research","type":"LIKE_COMMENT, LIKE_POST","weight":3},{"is_cross_platform":false,"source":"Compound","target":"Alameda Research","type":"LIKE_COMMENT, LIKE_POST","weight":3},{"is_cross_platform":false,"source":"Three Arrows Capital","target":"Alameda","type":"LIKE_COMMENT, LIKE_POST","weight":3},{"is_cross_platform":false,"source":"BTC","target":"Alameda","type":"LIKE_COMMENT, LIKE_POST","weight":3},{"is_cross_platform":false,"source":"Alameda Research","target":"Alameda","type":"LIKE_COMMENT, LIKE_POST","weight":3},{"is_cross_platform":false,"source":"Alameda Research","target":"FTX","type":"LIKE_COMMENT, LIKE_POST","weight":3},{"is_cross_platform":false,"source":"Solana","target":"FTX","type":"LIKE_COMMENT, LIKE_POST","weight":2},{"is_cross_platform":false,"source":"BTC","target":"FTX","type":"LIKE_COMMENT, LIKE_POST","weight":2},{"is_cross_platform":false,"source":"FTX","target":"Caroline Ellison","type":"DISLIKE_POST, LIKE_POST","weight":2},{"is_cross_platform":false,"source":"Celsius","target":"Solana","type":"LIKE_COMMENT","weight":2},{"is_cross_platform":false,"source":"ETH","target":"Solana","type":"LIKE_COMMENT","weight":2},{"is_cross_platform":false,"source":"Changpeng Zhao","target":"FTX","type":"LIKE_COMMENT, LIKE_POST","weight":2},{"is_cross_platform":false,"source":"Changpeng Zhao","target":"Solana","type":"LIKE_COMMENT","weight":2},{"is_cross_platform":false,"source":"Sam Bankman-Fried","target":"Alameda Research","type":"LIKE_COMMENT","weight":2},{"is_cross_platform":false,"source":"MakerDAO","target":"Binance","type":"FOLLOW, LIKE_COMMENT","weight":2},{"is_cross_platform":false,"source":"Binance","target":"BTC","type":"LIKE_COMMENT","weight":2},{"is_cross_platform":false,"source":"ETH","target":"CoinDesk","type":"LIKE_COMMENT, LIKE_POST","weight":2},{"is_cross_platform":false,"source":"Alameda","target":"SBF","type":"LIKE_COMMENT, LIKE_POST","weight":2},{"is_cross_platform":false,"source":"Caroline Ellison","target":"FTX","type":"DISLIKE_POST, LIKE_POST","weight":2},{"is_cross_platform":false,"source":"Caroline Ellison","target":"Compound","type":"LIKE_COMMENT, LIKE_POST","weight":2},{"is_cross_platform":false,"source":"Curve","target":"Alameda Research","type":"LIKE_COMMENT, LIKE_POST","weight":2},{"is_cross_platform":false,"source":"Aave","target":"Solana","type":"LIKE_COMMENT","weight":2},{"is_cross_platform":false,"source":"FTX","target":"Alameda Research","type":"LIKE_COMMENT, LIKE_POST","weight":2},{"is_cross_platform":false,"source":"BTC","target":"Changpeng Zhao","type":"DISLIKE_POST, LIKE_POST","weight":2},{"is_cross_platform":false,"source":"MakerDAO","target":"Alameda","type":"LIKE_COMMENT, LIKE_POST","weight":2},{"is_cross_platform":false,"source":"Compound","target":"Changpeng Zhao","type":"LIKE_COMMENT, LIKE_POST","weight":2},{"is_cross_platform":false,"source":"Binance","target":"Alameda Research","type":"LIKE_COMMENT","weight":2},{"is_cross_platform":false,"source":"Caroline Ellison","target":"Binance","type":"LIKE_COMMENT","weight":2},{"is_cross_platform":false,"source":"Caroline Ellison","target":"Alameda Research","type":"LIKE_COMMENT, LIKE_POST","weight":2},{"is_cross_platform":false,"source":"Changpeng Zhao","target":"Alameda","type":"LIKE_COMMENT, LIKE_POST","weight":2},{"is_cross_platform":false,"source":"Curve","target":"SBF","type":"DISLIKE_COMMENT","weight":2},{"is_cross_platform":false,"source":"Ian Allison","target":"BTC","type":"LIKE_COMMENT","weight":2},{"is_cross_platform":false,"source":"Voyager","target":"Binance","type":"LIKE_COMMENT","weight":2},{"is_cross_platform":false,"source":"Voyager","target":"Alameda","type":"LIKE_COMMENT, LIKE_POST","weight":2},{"is_cross_platform":false,"source":"Solana","target":"Caroline Ellison","type":"LIKE_POST","weight":2},{"is_cross_platform":false,"source":"Solana","target":"Alameda Research","type":"LIKE_COMMENT","weight":2},{"is_cross_platform":false,"source":"Solana","target":"Alameda","type":"LIKE_COMMENT, LIKE_POST","weight":2},{"is_cross_platform":false,"source":"Ian Allison","target":"Curve","type":"LIKE_COMMENT, LIKE_POST","weight":2},{"is_cross_platform":false,"source":"Caroline Ellison","target":"Alameda","type":"LIKE_COMMENT","weight":2},{"is_cross_platform":false,"source":"Aave","target":"FTT","type":"DISLIKE_COMMENT, LIKE_COMMENT","weight":2},{"is_cross_platform":false,"source":"FTX","target":"Alameda","type":"DISLIKE_POST, LIKE_COMMENT","weight":2},{"is_cross_platform":false,"source":"Changpeng Zhao","target":"ETH","type":"LIKE_COMMENT, LIKE_POST","weight":2},{"is_cross_platform":false,"source":"Changpeng Zhao","target":"SBF","type":"DISLIKE_COMMENT","weight":2},{"is_cross_platform":false,"source":"Changpeng Zhao","target":"CoinDesk","type":"DISLIKE_COMMENT, LIKE_POST","weight":2},{"is_cross_platform":false,"source":"Luna","target":"Alameda","type":"LIKE_COMMENT","weight":2},{"is_cross_platform":false,"source":"FTT","target":"SBF","type":"DISLIKE_COMMENT, DISLIKE_POST","weight":2},{"is_cross_platform":false,"source":"Voyager","target":"Solana","type":"LIKE_COMMENT","weight":2},{"is_cross_platform":false,"source":"FTT","target":"ETH","type":"DISLIKE_POST, LIKE_POST","weight":2},{"is_cross_platform":false,"source":"ETH","target":"Changpeng Zhao","type":"LIKE_POST","weight":2},{"is_cross_platform":false,"source":"Alameda Research","target":"Binance","type":"LIKE_COMMENT","weight":2},{"is_cross_platform":false,"source":"Alameda Research","target":"FTT","type":"DISLIKE_COMMENT, LIKE_COMMENT","weight":2},{"is_cross_platform":false,"source":"Sam Bankman-Fried","target":"Changpeng Zhao","type":"LIKE_COMMENT, LIKE_POST","weight":2},{"is_cross_platform":false,"source":"Sam Bankman-Fried","target":"FTX","type":"LIKE_COMMENT, LIKE_POST","weight":2},{"is_cross_platform":false,"source":"Ian Allison","target":"Compound","type":"DISLIKE_POST, LIKE_POST","weight":2},{"is_cross_platform":false,"source":"SBF","target":"Changpeng Zhao","type":"LIKE_POST","weight":2},{"is_cross_platform":false,"source":"Solana","target":"Ian Allison","type":"LIKE_POST","weight":1},{"is_cross_platform":false,"source":"Alameda","target":"Ian Allison","type":"LIKE_POST","weight":1},{"is_cross_platform":false,"source":"MakerDAO","target":"Ian Allison","type":"LIKE_POST","weight":1},{"is_cross_platform":false,"source":"FTX","target":"Ian Allison","type":"LIKE_POST","weight":1},{"is_cross_platform":false,"source":"Alameda Research","target":"Ian Allison","type":"LIKE_POST","weight":1},{"is_cross_platform":false,"source":"Three Arrows Capital","target":"Caroline Ellison","type":"DISLIKE_POST","weight":1},{"is_cross_platform":false,"source":"Celsius","target":"Ian Allison","type":"LIKE_POST","weight":1},{"is_cross_platform":false,"source":"Celsius","target":"Alameda Research","type":"LIKE_COMMENT","weight":1},{"is_cross_platform":false,"source":"Compound","target":"Ian Allison","type":"LIKE_POST","weight":1},{"is_cross_platform":false,"source":"Compound","target":"FTX","type":"LIKE_POST","weight":1},{"is_cross_platform":false,"source":"ETH","target":"FTX","type":"LIKE_POST","weight":1},{"is_cross_platform":false,"source":"Three Arrows Capital","target":"Ian Allison","type":"LIKE_POST","weight":1},{"is_cross_platform":false,"source":"Three Arrows Capital","target":"Alameda Research","type":"LIKE_COMMENT","weight":1},{"is_cross_platform":false,"source":"Ian Allison","target":"FTX","type":"LIKE_POST","weight":1},{"is_cross_platform":false,"source":"Solana","target":"Compound","type":"LIKE_POST","weight":1},{"is_cross_platform":false,"source":"SBF","target":"Caroline Ellison","type":"LIKE_POST","weight":1},{"is_cross_platform":false,"source":"Sam Bankman-Fried","target":"Luna","type":"LIKE_COMMENT","weight":1},{"is_cross_platform":false,"source":"Changpeng Zhao","target":"Ian Allison","type":"LIKE_POST","weight":1},{"is_cross_platform":false,"source":"Sam Bankman-Fried","target":"Compound","type":"LIKE_POST","weight":1},{"is_cross_platform":false,"source":"Sam Bankman-Fried","target":"Solana","type":"LIKE_COMMENT","weight":1},{"is_cross_platform":false,"source":"Three Arrows Capital","target":"Compound","type":"LIKE_POST","weight":1},{"is_cross_platform":false,"source":"Ian Allison","target":"Luna","type":"LIKE_COMMENT","weight":1},{"is_cross_platform":false,"source":"BTC","target":"SBF","type":"LIKE_POST","weight":1},{"is_cross_platform":false,"source":"BTC","target":"ETH","type":"DISLIKE_POST","weight":1},{"is_cross_platform":false,"source":"Three Arrows Capital","target":"Solana","type":"LIKE_COMMENT","weight":1},{"is_cross_platform":false,"source":"Caroline Ellison","target":"Changpeng Zhao","type":"LIKE_POST","weight":1},{"is_cross_platform":false,"source":"Curve","target":"FTX","type":"LIKE_COMMENT","weight":1},{"is_cross_platform":false,"source":"Aave","target":"Ian Allison","type":"LIKE_POST","weight":1},{"is_cross_platform":false,"source":"Curve","target":"Caroline Ellison","type":"DISLIKE_POST","weight":1},{"is_cross_platform":false,"source":"Aave","target":"FTX","type":"LIKE_POST","weight":1},{"is_cross_platform":false,"source":"FTX","target":"Solana","type":"LIKE_COMMENT","weight":1},{"is_cross_platform":false,"source":"SBF","target":"ETH","type":"LIKE_POST","weight":1},{"is_cross_platform":false,"source":"SBF","target":"CoinDesk","type":"LIKE_COMMENT","weight":1},{"is_cross_platform":false,"source":"Celsius","target":"ETH","type":"LIKE_POST","weight":1},{"is_cross_platform":false,"source":"CoinDesk","target":"FTX","type":"LIKE_POST","weight":1},{"is_cross_platform":false,"source":"Solana","target":"Changpeng Zhao","type":"LIKE_POST","weight":1},{"is_cross_platform":false,"source":"Three Arrows Capital","target":"SBF","type":"DISLIKE_COMMENT","weight":1},{"is_cross_platform":false,"source":"Alameda","target":"FTX","type":"LIKE_POST","weight":1},{"is_cross_platform":false,"source":"Alameda","target":"Compound","type":"LIKE_POST","weight":1},{"is_cross_platform":false,"source":"Binance","target":"Caroline Ellison","type":"DISLIKE_POST","weight":1},{"is_cross_platform":false,"source":"BUSD","target":"Alameda Research","type":"LIKE_COMMENT","weight":1},{"is_cross_platform":false,"source":"BUSD","target":"Solana","type":"LIKE_COMMENT","weight":1},{"is_cross_platform":false,"source":"Caroline Ellison","target":"SBF","type":"DISLIKE_COMMENT","weight":1},{"is_cross_platform":false,"source":"Changpeng Zhao","target":"Binance","type":"LIKE_COMMENT","weight":1},{"is_cross_platform":false,"source":"Ian Allison","target":"Alameda","type":"LIKE_COMMENT","weight":1},{"is_cross_platform":false,"source":"Ian Allison","target":"Binance","type":"LIKE_COMMENT","weight":1},{"is_cross_platform":false,"source":"Curve","target":"Solana","type":"LIKE_COMMENT","weight":1},{"is_cross_platform":false,"source":"FTT","target":"Ian Allison","type":"LIKE_POST","weight":1},{"is_cross_platform":false,"source":"Alameda","target":"Caroline Ellison","type":"LIKE_POST","weight":1},{"is_cross_platform":false,"source":"Voyager","target":"SBF","type":"LIKE_POST","weight":1},{"is_cross_platform":false,"source":"Voyager","target":"BTC","type":"LIKE_COMMENT","weight":1},{"is_cross_platform":false,"source":"Solana","target":"Binance","type":"LIKE_COMMENT","weight":1},{"is_cross_platform":false,"source":"BTC","target":"Curve","type":"LIKE_COMMENT","weight":1},{"is_cross_platform":false,"source":"Ian Allison","target":"Solana","type":"LIKE_COMMENT","weight":1},{"is_cross_platform":false,"source":"BTC","target":"Solana","type":"LIKE_COMMENT","weight":1},{"is_cross_platform":false,"source":"3AC","target":"ETH","type":"FOLLOW","weight":1},{"is_cross_platform":false,"source":"MakerDAO","target":"Curve","type":"LIKE_COMMENT","weight":1},{"is_cross_platform":false,"source":"MakerDAO","target":"FTT","type":"LIKE_COMMENT","weight":1},{"is_cross_platform":false,"source":"Aave","target":"Three Arrows Capital","type":"LIKE_COMMENT","weight":1},{"is_cross_platform":false,"source":"Binance","target":"CoinDesk","type":"DISLIKE_COMMENT","weight":1},{"is_cross_platform":false,"source":"Alameda","target":"Curve","type":"LIKE_POST","weight":1},{"is_cross_platform":false,"source":"Alameda","target":"Changpeng Zhao","type":"DISLIKE_POST","weight":1},{"is_cross_platform":false,"source":"SBF","target":"Alameda Research","type":"DISLIKE_COMMENT","weight":1},{"is_cross_platform":false,"source":"Changpeng Zhao","target":"Curve","type":"LIKE_COMMENT","weight":1},{"is_cross_platform":false,"source":"Celsius","target":"Curve","type":"LIKE_COMMENT","weight":1},{"is_cross_platform":false,"source":"Celsius","target":"Alameda","type":"LIKE_COMMENT","weight":1},{"is_cross_platform":false,"source":"Voyager","target":"Caroline Ellison","type":"LIKE_POST","weight":1},{"is_cross_platform":false,"source":"Binance","target":"Curve","type":"LIKE_POST","weight":1},{"is_cross_platform":false,"source":"Binance","target":"Alameda","type":"LIKE_COMMENT","weight":1},{"is_cross_platform":false,"source":"Changpeng Zhao","target":"MakerDAO","type":"LIKE_POST","weight":1},{"is_cross_platform":false,"source":"Solana","target":"Curve","type":"LIKE_POST","weight":1},{"is_cross_platform":false,"source":"Solana","target":"FTT","type":"LIKE_COMMENT","weight":1},{"is_cross_platform":false,"source":"CoinDesk","target":"Curve","type":"LIKE_POST","weight":1},{"is_cross_platform":false,"source":"CoinDesk","target":"MakerDAO","type":"DISLIKE_POST","weight":1},{"is_cross_platform":false,"source":"Luna","target":"Ian Allison","type":"LIKE_POST","weight":1},{"is_cross_platform":false,"source":"Luna","target":"Caroline Ellison","type":"LIKE_POST","weight":1},{"is_cross_platform":false,"source":"Luna","target":"SBF","type":"LIKE_COMMENT","weight":1},{"is_cross_platform":false,"source":"FTT","target":"MakerDAO","type":"LIKE_POST","weight":1},{"is_cross_platform":false,"source":"FTX","target":"Three Arrows Capital","type":"LIKE_COMMENT","weight":1},{"is_cross_platform":false,"source":"Binance","target":"Ian Allison","type":"LIKE_POST","weight":1},{"is_cross_platform":false,"source":"Binance","target":"MakerDAO","type":"LIKE_POST","weight":1},{"is_cross_platform":false,"source":"Binance","target":"FTX","type":"LIKE_COMMENT","weight":1},{"is_cross_platform":false,"source":"Binance","target":"Solana","type":"LIKE_COMMENT","weight":1},{"is_cross_platform":false,"source":"Binance","target":"FTT","type":"LIKE_COMMENT","weight":1},{"is_cross_platform":false,"source":"Binance","target":"Aave","type":"LIKE_COMMENT","weight":1},{"is_cross_platform":false,"source":"Voyager","target":"Curve","type":"LIKE_POST","weight":1},{"is_cross_platform":false,"source":"3AC","target":"Ian Allison","type":"LIKE_POST","weight":1},{"is_cross_platform":false,"source":"Voyager","target":"Three Arrows Capital","type":"LIKE_COMMENT","weight":1},{"is_cross_platform":false,"source":"FTT","target":"Changpeng Zhao","type":"LIKE_POST","weight":1},{"is_cross_platform":false,"source":"FTT","target":"Curve","type":"LIKE_COMMENT","weight":1},{"is_cross_platform":false,"source":"FTT","target":"Solana","type":"LIKE_COMMENT","weight":1},{"is_cross_platform":false,"source":"ETH","target":"Alameda","type":"LIKE_POST","weight":1},{"is_cross_platform":false,"source":"SBF","target":"Ian Allison","type":"LIKE_POST","weight":1},{"is_cross_platform":false,"source":"ETH","target":"Compound","type":"LIKE_POST","weight":1},{"is_cross_platform":false,"source":"Caroline Ellison","target":"Curve","type":"LIKE_POST","weight":1},{"is_cross_platform":false,"source":"Caroline Ellison","target":"Solana","type":"LIKE_COMMENT","weight":1},{"is_cross_platform":false,"source":"CoinDesk","target":"Changpeng Zhao","type":"LIKE_POST","weight":1},{"is_cross_platform":false,"source":"CoinDesk","target":"Celsius","type":"LIKE_COMMENT","weight":1},{"is_cross_platform":false,"source":"FTX","target":"Curve","type":"LIKE_POST","weight":1},{"is_cross_platform":false,"source":"ETH","target":"SBF","type":"DISLIKE_POST","weight":1},{"is_cross_platform":false,"source":"ETH","target":"MakerDAO","type":"DISLIKE_POST","weight":1},{"is_cross_platform":false,"source":"Voyager","target":"Ian Allison","type":"LIKE_POST","weight":1},{"is_cross_platform":false,"source":"Voyager","target":"FTT","type":"LIKE_COMMENT","weight":1},{"is_cross_platform":false,"source":"Voyager","target":"Aave","type":"LIKE_COMMENT","weight":1},{"is_cross_platform":false,"source":"Ian Allison","target":"FTT","type":"LIKE_COMMENT","weight":1},{"is_cross_platform":false,"source":"Ian Allison","target":"SBF","type":"LIKE_POST","weight":1},{"is_cross_platform":false,"source":"Ian Allison","target":"ETH","type":"DISLIKE_POST","weight":1},{"is_cross_platform":false,"source":"CoinDesk","target":"Alameda","type":"LIKE_COMMENT","weight":1},{"is_cross_platform":false,"source":"Sam Bankman-Fried","target":"Ian Allison","type":"LIKE_POST","weight":1},{"is_cross_platform":false,"source":"Sam Bankman-Fried","target":"Curve","type":"LIKE_COMMENT","weight":1},{"is_cross_platform":false,"source":"MakerDAO","target":"Changpeng Zhao","type":"LIKE_POST","weight":1},{"is_cross_platform":false,"source":"FTX","target":"Binance","type":"LIKE_COMMENT","weight":1},{"is_cross_platform":false,"source":"Luna","target":"Three Arrows Capital","type":"LIKE_COMMENT","weight":1},{"is_cross_platform":false,"source":"Alameda Research","target":"Three Arrows Capital","type":"LIKE_COMMENT","weight":1},{"is_cross_platform":false,"source":"Luna","target":"Changpeng Zhao","type":"LIKE_COMMENT","weight":1},{"is_cross_platform":false,"source":"Alameda Research","target":"Voyager","type":"LIKE_COMMENT","weight":1},{"is_cross_platform":false,"source":"Alameda","target":"MakerDAO","type":"LIKE_POST","weight":1},{"is_cross_platform":false,"source":"Alameda","target":"ETH","type":"DISLIKE_POST","weight":1},{"is_cross_platform":false,"source":"Solana","target":"ETH","type":"LIKE_POST","weight":1},{"is_cross_platform":false,"source":"FTT","target":"BTC","type":"LIKE_COMMENT","weight":1},{"is_cross_platform":false,"source":"Alameda Research","target":"MakerDAO","type":"LIKE_POST","weight":1},{"is_cross_platform":false,"source":"Changpeng Zhao","target":"Caroline Ellison","type":"LIKE_POST","weight":1},{"is_cross_platform":false,"source":"SBF","target":"Luna","type":"LIKE_POST","weight":1},{"is_cross_platform":false,"source":"Sam Bankman-Fried","target":"FTT","type":"LIKE_COMMENT","weight":1},{"is_cross_platform":false,"source":"Sam Bankman-Fried","target":"Binance","type":"LIKE_COMMENT","weight":1},{"is_cross_platform":false,"source":"MakerDAO","target":"Compound","type":"LIKE_POST","weight":1},{"is_cross_platform":false,"source":"MakerDAO","target":"CoinDesk","type":"LIKE_POST","weight":1},{"is_cross_platform":false,"source":"Alameda Research","target":"Luna","type":"LIKE_POST","weight":1},{"is_cross_platform":false,"source":"3AC","target":"Compound","type":"LIKE_POST","weight":1},{"is_cross_platform":false,"source":"3AC","target":"CoinDesk","type":"LIKE_POST","weight":1},{"is_cross_platform":false,"source":"BTC","target":"MakerDAO","type":"LIKE_POST","weight":1},{"is_cross_platform":false,"source":"BTC","target":"CoinDesk","type":"LIKE_POST","weight":1},{"is_cross_platform":false,"source":"FTT","target":"Alameda Research","type":"LIKE_COMMENT","weight":1},{"is_cross_platform":false,"source":"FTT","target":"Alameda","type":"LIKE_COMMENT","weight":1},{"is_cross_platform":false,"source":"Luna","target":"FTT","type":"LIKE_COMMENT","weight":1},{"is_cross_platform":false,"source":"Luna","target":"Binance","type":"LIKE_COMMENT","weight":1},{"is_cross_platform":false,"source":"Luna","target":"BTC","type":"LIKE_COMMENT","weight":1},{"is_cross_platform":false,"source":"Curve","target":"BTC","type":"LIKE_POST","weight":1},{"is_cross_platform":false,"source":"Ian Allison","target":"Voyager","type":"LIKE_POST","weight":1},{"is_cross_platform":false,"source":"Aave","target":"Alameda","type":"LIKE_POST","weight":1},{"is_cross_platform":false,"source":"Aave","target":"ETH","type":"LIKE_COMMENT","weight":1},{"is_cross_platform":false,"source":"Aave","target":"BUSD","type":"LIKE_COMMENT","weight":1},{"is_cross_platform":false,"source":"Alameda","target":"Luna","type":"LIKE_POST","weight":1},{"is_cross_platform":false,"source":"Alameda","target":"Binance","type":"LIKE_COMMENT","weight":1},{"is_cross_platform":false,"source":"Alameda","target":"CoinDesk","type":"LIKE_COMMENT","weight":1},{"is_cross_platform":false,"source":"Alameda","target":"Three Arrows Capital","type":"LIKE_COMMENT","weight":1},{"is_cross_platform":false,"source":"Alameda Research","target":"Curve","type":"LIKE_POST","weight":1},{"is_cross_platform":false,"source":"Alameda Research","target":"BTC","type":"LIKE_COMMENT","weight":1},{"is_cross_platform":false,"source":"Compound","target":"MakerDAO","type":"LIKE_POST","weight":1},{"is_cross_platform":false,"source":"SBF","target":"Alameda","type":"LIKE_POST","weight":1}],"nodes":[{"id":"Ian Allison","in_degree":17,"influence_score":57,"name":"Ian Allison","out_degree":15,"platforms":["reddit"],"rank":2,"stance":"neutral","total_degree":32,"type":"reddit"},{"id":"FTX","in_degree":41,"influence_score":60,"name":"FTX","out_degree":20,"platforms":["reddit"],"rank":1,"stance":"neutral","total_degree":61,"type":"reddit"},{"id":"SBF","in_degree":34,"influence_score":28,"name":"SBF","out_degree":13,"platforms":["reddit"],"rank":9,"stance":"neutral","total_degree":47,"type":"reddit"},{"id":"Caroline Ellison","in_degree":25,"influence_score":52,"name":"Caroline Ellison","out_degree":17,"platforms":["reddit"],"rank":3,"stance":"neutral","total_degree":42,"type":"reddit"},{"id":"Luna","in_degree":5,"influence_score":16,"name":"Luna","out_degree":17,"platforms":["reddit"],"rank":13,"stance":"neutral","total_degree":22,"type":"reddit"},{"id":"ETH","in_degree":12,"influence_score":24,"name":"ETH","out_degree":11,"platforms":["reddit"],"rank":11,"stance":"neutral","total_degree":23,"type":"reddit"},{"id":"Solana","in_degree":20,"influence_score":5,"name":"Solana","out_degree":15,"platforms":["reddit"],"rank":18,"stance":"neutral","total_degree":35,"type":"reddit"},{"id":"Alameda","in_degree":31,"influence_score":37,"name":"Alameda","out_degree":14,"platforms":["reddit"],"rank":5,"stance":"neutral","total_degree":45,"type":"reddit"},{"id":"MakerDAO","in_degree":9,"influence_score":27,"name":"MakerDAO","out_degree":16,"platforms":["reddit"],"rank":10,"stance":"neutral","total_degree":25,"type":"reddit"},{"id":"BTC","in_degree":20,"influence_score":9,"name":"BTC","out_degree":16,"platforms":["reddit"],"rank":14,"stance":"neutral","total_degree":36,"type":"reddit"},{"id":"Alameda Research","in_degree":32,"influence_score":32,"name":"Alameda Research","out_degree":26,"platforms":["reddit"],"rank":8,"stance":"neutral","total_degree":58,"type":"reddit"},{"id":"Three Arrows Capital","in_degree":6,"influence_score":5,"name":"Three Arrows Capital","out_degree":18,"platforms":["reddit"],"rank":19,"stance":"neutral","total_degree":24,"type":"reddit"},{"id":"Celsius","in_degree":1,"influence_score":5,"name":"Celsius","out_degree":7,"platforms":["reddit"],"rank":20,"stance":"neutral","total_degree":8,"type":"reddit"},{"id":"Binance","in_degree":15,"influence_score":7,"name":"Binance","out_degree":19,"platforms":["reddit"],"rank":16,"stance":"neutral","total_degree":34,"type":"reddit"},{"id":"Compound","in_degree":11,"influence_score":34,"name":"Compound","out_degree":8,"platforms":["reddit"],"rank":7,"stance":"neutral","total_degree":19,"type":"reddit"},{"id":"FTT","in_degree":11,"influence_score":5,"name":"FTT","out_degree":19,"platforms":["reddit"],"rank":21,"stance":"neutral","total_degree":30,"type":"reddit"},{"id":"Sam Bankman-Fried","in_degree":0,"influence_score":5,"name":"Sam Bankman-Fried","out_degree":13,"platforms":["reddit"],"rank":22,"stance":"neutral","total_degree":13,"type":"reddit"},{"id":"Curve","in_degree":19,"influence_score":36,"name":"Curve","out_degree":8,"platforms":["reddit"],"rank":6,"stance":"neutral","total_degree":27,"type":"reddit"},{"id":"Changpeng Zhao","in_degree":17,"influence_score":43,"name":"Changpeng Zhao","out_degree":17,"platforms":["reddit"],"rank":4,"stance":"neutral","total_degree":34,"type":"reddit"},{"id":"CoinDesk","in_degree":10,"influence_score":22,"name":"CoinDesk","out_degree":6,"platforms":["reddit"],"rank":12,"stance":"neutral","total_degree":16,"type":"reddit"},{"id":"Aave","in_degree":2,"influence_score":5,"name":"Aave","out_degree":17,"platforms":["reddit"],"rank":23,"stance":"neutral","total_degree":19,"type":"reddit"},{"id":"BUSD","in_degree":1,"influence_score":6,"name":"BUSD","out_degree":2,"platforms":["reddit"],"rank":17,"stance":"neutral","total_degree":3,"type":"reddit"},{"id":"Voyager","in_degree":2,"influence_score":9,"name":"Voyager","out_degree":23,"platforms":["reddit"],"rank":15,"stance":"neutral","total_degree":25,"type":"reddit"},{"id":"3AC","in_degree":0,"influence_score":5,"name":"3AC","out_degree":4,"platforms":["reddit"],"rank":24,"stance":"neutral","total_degree":4,"type":"reddit"}]},"insights":{"echo_chamber":{"description":"100.0% of interactions were within the same platform. Agents mostly stayed in their silos.","score":100.0},"top_bridge":null,"top_hub":{"agent":"FTX","description":"FTX received 41 interactions \u2014 more than any other agent.","in_degree":41},"total_edges":225,"total_nodes":24},"node_count":24,"run_id":"demo_20260426_102814_381d01","sim_id":"sim_4c9f891f53ee"}
